Metadata-Version: 2.1
Name: uncurl-seq
Version: 0.2.16
Summary: Tool for pre-processing single-cell RNASeq data
Home-page: https://github.com/yjzhang/uncurl_python
Author: Yue Zhang
Author-email: yjzhang@cs.washington.edu
License: MIT
Platform: UNKNOWN
Classifier: Development Status :: 3 - Alpha
Classifier: Topic :: Scientific/Engineering :: Bio-Informatics
Classifier: License :: OSI Approved :: MIT License
Classifier: Programming Language :: Python :: 2.7
Classifier: Programming Language :: Python :: 3.5
License-File: LICENSE
